[
    {
        "文件类型": null,
        "文件名称": null,
        "文件含义": null,
        "编码": null,
        "编码含义": null,
        "变更数据项（节点）": null,
        "变更数据项含义": null,
        "变更具体描述": null,
        "变更项变更前内容": null,
        "变更项变更后内容": null,
        "备注": null
    },
    {
        "文件类型": "空运航线航班空备案",
        "文件名称": "CAM001Message.xsd",
        "文件含义": "空运航线航班空备案申请",
        "编码": "CAM001",
        "编码含义": "空运航线航班空备案",
        "变更数据项（节点）": "Message:MessageBody:Declaration:airCraftRecord:CabinSeating",
        "变更数据项含义": "客舱座位分布图",
        "变更具体描述": "JPG格式图片，以base64编码方式传输，最大不超过200K",
        "变更项变更前内容": null,
        "变更项变更后内容": " <xs:element name=\"CabinSeating\" type=\"wco552\" minOccurs=\"0\">",
        "备注": "新增节点"
    },
    {
        "文件类型": "空运通用航班空备案",
        "文件名称": "CAM011Message.xsd",
        "文件含义": "空运通用航班空备案申请",
        "编码": "CAM011",
        "编码含义": "空运通用航班空备案",
        "变更数据项（节点）": "Message:MessageBody:Declaration:airCraftRecord:CabinSeating",
        "变更数据项含义": "客舱座位分布图",
        "变更具体描述": "JPG格式图片，以base64编码方式传输，最大不超过200K",
        "变更项变更前内容": null,
        "变更项变更后内容": " <xs:element name=\"CabinSeating\" type=\"wco552\" minOccurs=\"0\">",
        "备注": "新增节点"
    },
    {
        "文件类型": null,
        "文件名称": null,
        "文件含义": null,
        "编码": null,
        "编码含义": null,
        "变更数据项（节点）": null,
        "变更数据项含义": null,
        "变更具体描述": null,
        "变更项变更前内容": null,
        "变更项变更后内容": null,
        "备注": null
    },
    {
        "文件类型": "水运船舶备案",
        "文件名称": "CSM001Message.xsd",
        "文件含义": "水运船舶备案申报",
        "编码": "CSM001",
        "编码含义": "水运船舶备案",
        "变更数据项（节点）": "Message:MessageBody:Declaration:Archive:MmsiNumber",
        "变更数据项含义": "AIS 设备 MMSI 编码",
        "变更具体描述": "数据项字段长度最大为25位",
        "变更项变更前内容": null,
        "变更项变更后内容": "<xs:element name=\"MmsiNumber\"  minOccurs=\"0\" >",
        "备注": "新增节点"
    },
    {
        "文件类型": "水运船舶备案",
        "文件名称": "CSM001Message.xsd",
        "文件含义": "水运船舶备案申报",
        "编码": "CSM001",
        "编码含义": "水运船舶备案",
        "变更数据项（节点）": "Message:MessageBody:Declaration:Archive:SimCode",
        "变更数据项含义": "船载收发信装置SIM卡号码",
        "变更具体描述": "数据项字段长度最大为16位",
        "变更项变更前内容": null,
        "变更项变更后内容": "<xs:element name=\"SimCode\"  minOccurs=\"0\" >",
        "备注": "新增节点"
    },
    {
        "文件类型": "水运船舶备案",
        "文件名称": "CSM001Message.xsd",
        "文件含义": "水运船舶备案申报",
        "编码": "CSM001",
        "编码含义": "水运船舶备案",
        "变更数据项（节点）": "Message:MessageBody:Declaration:Archive:TerminalId",
        "变更数据项含义": "船载收发信装置ID号",
        "变更具体描述": "数据项字段长度最大为10位",
        "变更项变更前内容": null,
        "变更项变更后内容": " <xs:element name=\"TerminalId\"  minOccurs=\"0\" >",
        "备注": "新增节点"
    },
    {
        "文件类型": null,
        "文件名称": null,
        "文件含义": null,
        "编码": null,
        "编码含义": null,
        "变更数据项（节点）": null,
        "变更数据项含义": null,
        "变更具体描述": null,
        "变更项变更前内容": null,
        "变更项变更后内容": null,
        "备注": null
    },
    {
        "文件类型": "船舶进境（港）预报动态",
        "文件名称": "CSM002Message.xsd",
        "文件含义": "船舶进境（港）预报动态申报",
        "编码": "CSM002",
        "编码含义": "船舶进境（港）预报动态",
        "变更数据项（节点）": "Message:MessageBody:Declaration:BorderTransPortMeans:IsMidwayStation",
        "变更数据项含义": "需要中途监管",
        "变更具体描述": "枚举类型：T表示需要中途监管；F表示不需要中途监管。节点可无或传入空值",
        "变更项变更前内容": null,
        "变更项变更后内容": "<xs:element name=\"IsMidwayStation\"  minOccurs=\"0\" >",
        "备注": "新增节点"
    },
    {
        "文件类型": "船舶进境（港）预报动态",
        "文件名称": "CSM002Message.xsd",
        "文件含义": "船舶进境（港）预报动态申报",
        "编码": "CSM002",
        "编码含义": "船舶进境（港）预报动态",
        "变更数据项（节点）": "Message:MessageBody:Declaration:BorderTransPortMeans:MidwayStation",
        "变更数据项含义": "中途监管站",
        "变更具体描述": "枚举类型：5149，5331，5794，5741。节点可无或传入空值",
        "变更项变更前内容": null,
        "变更项变更后内容": "<xs:element name=\"MidwayStation\" minOccurs=\"0\" >",
        "备注": "新增节点"
    },
    {
        "文件类型": null,
        "文件名称": null,
        "文件含义": null,
        "编码": null,
        "编码含义": null,
        "变更数据项（节点）": null,
        "变更数据项含义": null,
        "变更具体描述": null,
        "变更项变更前内容": null,
        "变更项变更后内容": null,
        "备注": null
    },
    {
        "文件类型": "船舶进境（港）确报动态",
        "文件名称": "CSM003Message.xsd",
        "文件含义": "船舶进境（港）确报动态申报",
        "编码": "CSM003",
        "编码含义": "船舶进境（港）确报动态",
        "变更数据项（节点）": "Message:MessageBody:Declaration:BorderTransPortMeans:IsMidwayStation",
        "变更数据项含义": "需要中途监管",
        "变更具体描述": "枚举类型：T表示需要中途监管；F表示不需要中途监管。节点可无或传入空值",
        "变更项变更前内容": null,
        "变更项变更后内容": "<xs:element name=\"IsMidwayStation\"  minOccurs=\"0\" >",
        "备注": "新增节点"
    },
    {
        "文件类型": "船舶进境（港）确报动态",
        "文件名称": "CSM003Message.xsd",
        "文件含义": "船舶进境（港）确报动态申报",
        "编码": "CSM003",
        "编码含义": "船舶进境（港）确报动态",
        "变更数据项（节点）": "Message:MessageBody:Declaration:BorderTransPortMeans:MidwayStation",
        "变更数据项含义": "中途监管站",
        "变更具体描述": "枚举类型：5149，5331，5794，5741。节点可无或传入空值",
        "变更项变更前内容": null,
        "变更项变更后内容": "<xs:element name=\"MidwayStation\" minOccurs=\"0\" >",
        "备注": "新增节点"
    },
    {
        "文件类型": null,
        "文件名称": null,
        "文件含义": null,
        "编码": null,
        "编码含义": null,
        "变更数据项（节点）": null,
        "变更数据项含义": null,
        "变更具体描述": null,
        "变更项变更前内容": null,
        "变更项变更后内容": null,
        "备注": null
    },
    {
        "文件类型": "船舶进境（港）抵港动态",
        "文件名称": "CSM004Message.xsd",
        "文件含义": "船舶进境（港）抵港动态申报",
        "编码": "CSM004",
        "编码含义": "船舶进境（港）抵港动态",
        "变更数据项（节点）": "Message:MessageBody:Declaration:BorderTransPortMeans:IsMidwayStation",
        "变更数据项含义": "需要中途监管",
        "变更具体描述": "枚举类型：T表示需要中途监管；F表示不需要中途监管。节点可无或传入空值",
        "变更项变更前内容": null,
        "变更项变更后内容": "<xs:element name=\"IsMidwayStation\"  minOccurs=\"0\" >",
        "备注": "新增节点"
    },
    {
        "文件类型": "船舶进境（港）抵港动态",
        "文件名称": "CSM004Message.xsd",
        "文件含义": "船舶进境（港）抵港动态申报",
        "编码": "CSM004",
        "编码含义": "船舶进境（港）抵港动态",
        "变更数据项（节点）": "Message:MessageBody:Declaration:BorderTransPortMeans:MidwayStation",
        "变更数据项含义": "中途监管站",
        "变更具体描述": "枚举类型：5149，5331，5794，5741。节点可无或传入空值",
        "变更项变更前内容": null,
        "变更项变更后内容": "<xs:element name=\"MidwayStation\" minOccurs=\"0\" >",
        "备注": "新增节点"
    },
    {
        "文件类型": null,
        "文件名称": null,
        "文件含义": null,
        "编码": null,
        "编码含义": null,
        "变更数据项（节点）": null,
        "变更数据项含义": null,
        "变更具体描述": null,
        "变更项变更前内容": null,
        "变更项变更后内容": null,
        "备注": null
    },
    {
        "文件类型": "船舶离境（港）预报动态",
        "文件名称": "CSM006Message.xsd",
        "文件含义": "船舶离境（港）预报动态申报",
        "编码": "CSM006",
        "编码含义": "船舶离境（港）预报动态",
        "变更数据项（节点）": "Message:MessageBody:Declaration:BorderTransPortMeans:IsMidwayStation",
        "变更数据项含义": "需要中途监管",
        "变更具体描述": "枚举类型：T表示需要中途监管；F表示不需要中途监管。节点可无或传入空值",
        "变更项变更前内容": null,
        "变更项变更后内容": "<xs:element name=\"IsMidwayStation\"  minOccurs=\"0\" >",
        "备注": "新增节点"
    },
    {
        "文件类型": "船舶离境（港）预报动态",
        "文件名称": "CSM006Message.xsd",
        "文件含义": "船舶离境（港）预报动态申报",
        "编码": "CSM006",
        "编码含义": "船舶离境（港）预报动态",
        "变更数据项（节点）": "Message:MessageBody:Declaration:BorderTransPortMeans:MidwayStation",
        "变更数据项含义": "中途监管站",
        "变更具体描述": "枚举类型：5149，5331，5794，5741。节点可无或传入空值",
        "变更项变更前内容": null,
        "变更项变更后内容": "<xs:element name=\"MidwayStation\" minOccurs=\"0\" >",
        "备注": "新增节点"
    },
    {
        "文件类型": null,
        "文件名称": null,
        "文件含义": null,
        "编码": null,
        "编码含义": null,
        "变更数据项（节点）": null,
        "变更数据项含义": null,
        "变更具体描述": null,
        "变更项变更前内容": null,
        "变更项变更后内容": null,
        "备注": null
    },
    {
        "文件类型": "船舶离境（港）确报动态",
        "文件名称": "CSM007Message.xsd",
        "文件含义": "船舶离境（港）确报动态申报",
        "编码": "CSM007",
        "编码含义": "船舶离境（港）确报动态",
        "变更数据项（节点）": "Message:MessageBody:Declaration:BorderTransPortMeans:IsMidwayStation",
        "变更数据项含义": "需要中途监管",
        "变更具体描述": "枚举类型：T表示需要中途监管；F表示不需要中途监管。节点可无或传入空值",
        "变更项变更前内容": null,
        "变更项变更后内容": "<xs:element name=\"IsMidwayStation\"  minOccurs=\"0\" >",
        "备注": "新增节点"
    },
    {
        "文件类型": "船舶离境（港）确报动态",
        "文件名称": "CSM007Message.xsd",
        "文件含义": "船舶离境（港）确报动态申报",
        "编码": "CSM007",
        "编码含义": "船舶离境（港）确报动态",
        "变更数据项（节点）": "Message:MessageBody:Declaration:BorderTransPortMeans:MidwayStation",
        "变更数据项含义": "中途监管站",
        "变更具体描述": "枚举类型：5149，5331，5794，5741。节点可无或传入空值",
        "变更项变更前内容": null,
        "变更项变更后内容": "<xs:element name=\"MidwayStation\" minOccurs=\"0\" >",
        "备注": "新增节点"
    },
    {
        "文件类型": null,
        "文件名称": null,
        "文件含义": null,
        "编码": null,
        "编码含义": null,
        "变更数据项（节点）": null,
        "变更数据项含义": null,
        "变更具体描述": null,
        "变更项变更前内容": null,
        "变更项变更后内容": null,
        "备注": null
    },
    {
        "文件类型": "水运供退物料",
        "文件名称": "CSM102Message.xsd",
        "文件含义": "水运供退物料申报",
        "编码": "CSM102",
        "编码含义": "水运供退物料",
        "变更数据项（节点）": "Message:MessageBody:Declaration:Material:Header:Bill_Num",
        "变更数据项含义": "随附单据页数",
        "变更具体描述": "节点去掉（原：数据项字段整数类型，最大999）",
        "变更项变更前内容": null,
        "变更项变更后内容": "<xs:element name=\"Bill_Num\" type=\"N3Empty\" minOccurs=\"0\">",
        "备注": "删除节点"
    },
    {
        "文件类型": "水运供退物料",
        "文件名称": "CSM102Message.xsd",
        "文件含义": "水运供退物料申报",
        "编码": "CSM102",
        "编码含义": "水运供退物料",
        "变更数据项（节点）": "Message:MessageBody:Declaration:Material:Header:Bill_Type",
        "变更数据项含义": "随附单据种类",
        "变更具体描述": "节点去掉（原：数据项字段最大长度为35）",
        "变更项变更前内容": null,
        "变更项变更后内容": "<xs:element name=\"Bill_Type\" type=\"X35\" minOccurs=\"0\">",
        "备注": "删除节点"
    },
    {
        "文件类型": "水运供退物料",
        "文件名称": "CSM102Message.xsd",
        "文件含义": "水运供退物料申报",
        "编码": "CSM102",
        "编码含义": "水运供退物料",
        "变更数据项（节点）": "Message:MessageBody:Declaration:Material:Header:Other",
        "变更数据项含义": "其他单据页数",
        "变更具体描述": "节点去掉（原：数据项字段最大长度为10）",
        "变更项变更前内容": null,
        "变更项变更后内容": "<xs:element name=\"Other\" minOccurs=\"0\">",
        "备注": "删除节点"
    },
    {
        "文件类型": "水运供退物料",
        "文件名称": "CSM102Message.xsd",
        "文件含义": "水运供退物料申报",
        "编码": "CSM102",
        "编码含义": "水运供退物料",
        "变更数据项（节点）": "Message:MessageBody:Declaration:Material:Header:PlanSupplyTime",
        "变更数据项含义": "计划供退时间",
        "变更具体描述": "数据项字段长度为12位，格式为：yyyyMMddHHmm",
        "变更项变更前内容": null,
        "变更项变更后内容": "<xs:element name=\"PlanSupplyTime\" type=\"wco578\" minOccurs=\"0\">",
        "备注": "新增节点"
    }
]